dbdemos_tracker/__init__.py
dbdemos_tracker/tracker.py
dbdemos_tracker-0.1.12.dist-info/LICENSE
dbdemos_tracker-0.1.12.dist-info/METADATA
dbdemos_tracker-0.1.12.dist-info/WHEEL
dbdemos_tracker-0.1.12.dist-info/top_level.txt
dbdemos_tracker-0.1.12.dist-info/RECORD
