Metadata-Version: 2.1
Name: dbdemos-tracker
Version: 0.1.12
Summary: A tracking library for Databricks demo analytics.
Home-page: https://github.com/databricks-field-eng/dbdemos-tracker
Author: Databricks
Author-email: quentin.ambard@databricks.com
License: Databricks license
Requires-Python: >=3.7
License-File: LICENSE
Requires-Dist: requests >=2.25.0
Requires-Dist: databricks-sdk >=0.8.0
Provides-Extra: dev
Requires-Dist: fastapi >=0.68.0 ; extra == 'dev'
Requires-Dist: pytest >=6.0 ; extra == 'dev'
Requires-Dist: pytest-cov >=2.0 ; extra == 'dev'
Requires-Dist: black >=21.0 ; extra == 'dev'
Requires-Dist: flake8 >=3.8 ; extra == 'dev'
Provides-Extra: test
Requires-Dist: pytest >=6.0 ; extra == 'test'
Requires-Dist: pytest-cov >=2.0 ; extra == 'test'
Requires-Dist: fastapi >=0.68.0 ; extra == 'test'
Requires-Dist: httpx >=0.24.0 ; extra == 'test'
